deepground/__init__.py
deepground/core.py
deepground-0.8.2.dist-info/METADATA
deepground-0.8.2.dist-info/WHEEL
deepground-0.8.2.dist-info/top_level.txt
deepground-0.8.2.dist-info/RECORD
