Metadata-Version: 2.4
Name: deepground
Version: 0.8.2
Summary: Deepground - A Python library that empowers LLM agents with real-time data access from both the clear and dark net.
Home-page: https://github.com/evilfeonix/deepground
Author: Evilfeonix
Author-email: Evilfeonix <evilfeonix@proton.me>
License: MIT
Project-URL: Homepage, https://github.com/evilfeonix/deepground
Project-URL: Issues, https://github.com/evilfeonix/deepground/issues
Keywords: LLM,real-time,darknet,search,osint,tor,ai,darkweb,groundX,groundnet,deepground,grounder,evilfeonix,grounding info,information gathering
Requires-Python: >=3.10
Requires-Dist: requests[socks]
Requires-Dist: aiohttp
Requires-Dist: ddgs
Requires-Dist: aiohttp-socks
Requires-Dist: beautifulsoup4
Requires-Dist: langchain
Requires-Dist: typing-extensions
Dynamic: author
Dynamic: home-page
Dynamic: requires-python
